{
  "id": 116,
  "image_file": "AMBER_116.jpg",
  "query_text": "Describe this image.",
  "response": "The image features a lush green field with three children playing together. Two of the children are standing close to each other, while the third child is positioned slightly further away. They are all enjoying their time outdoors, possibly playing with a toy.\n\nIn the scene, there is a toy car visible on the ground, adding to the playful atmosphere. The children are spread out across the field, with one child on the left side, another in the middle, and the third on the right side.",
  "token_ids": [
    450,
    1967,
    5680,
    263,
    301,
    1878,
    7933,
    1746,
    411,
    2211,
    4344,
    8743,
    4208,
    29889,
    7803,
    310,
    278,
    4344,
    526,
    13407,
    3802,
    304,
    1269,
    916,
    29892,
    1550,
    278,
    4654,
    2278,
    338,
    2602,
    287,
    10029,
    4340,
    3448,
    29889,
    2688,
    526,
    599,
    11418,
    5414,
    1009,
    931,
    714,
    1867,
    943,
    29892,
    10075,
    8743,
    411,
    263,
    304,
    29891,
    29889,
    13,
    13,
    797,
    278,
    9088,
    29892,
    727,
    338,
    263,
    304,
    29891,
    1559,
    7962,
    373,
    278,
    5962,
    29892,
    4417,
    304,
    278,
    1708,
    1319,
    25005,
    29889,
    450,
    4344,
    526,
    9677,
    714,
    4822,
    278,
    1746,
    29892,
    411,
    697,
    2278,
    373,
    278,
    2175,
    2625,
    29892,
    1790,
    297,
    278,
    7256,
    29892,
    322,
    278,
    4654,
    373,
    278,
    1492,
    2625,
    29889
  ],
  "tokens": [
    "The",
    "image",
    "features",
    "a",
    "l",
    "ush",
    "green",
    "field",
    "with",
    "three",
    "children",
    "playing",
    "together",
    ".",
    "Two",
    "of",
    "the",
    "children",
    "are",
    "standing",
    "close",
    "to",
    "each",
    "other",
    ",",
    "while",
    "the",
    "third",
    "child",
    "is",
    "position",
    "ed",
    "slightly",
    "further",
    "away",
    ".",
    "They",
    "are",
    "all",
    "enjo",
    "ying",
    "their",
    "time",
    "out",
    "do",
    "ors",
    ",",
    "possibly",
    "playing",
    "with",
    "a",
    "to",
    "y",
    ".",
    "\n",
    "\n",
    "In",
    "the",
    "scene",
    ",",
    "there",
    "is",
    "a",
    "to",
    "y",
    "car",
    "visible",
    "on",
    "the",
    "ground",
    ",",
    "adding",
    "to",
    "the",
    "play",
    "ful",
    "atmosphere",
    ".",
    "The",
    "children",
    "are",
    "spread",
    "out",
    "across",
    "the",
    "field",
    ",",
    "with",
    "one",
    "child",
    "on",
    "the",
    "left",
    "side",
    ",",
    "another",
    "in",
    "the",
    "middle",
    ",",
    "and",
    "the",
    "third",
    "on",
    "the",
    "right",
    "side",
    "."
  ],
  "token_types": [
    "other",
    "other",
    "other",
    "other",
    "other",
    "other",
    "other",
    "other",
    "other",
    "other",
    "object",
    "other",
    "other",
    "other",
    "other",
    "other",
    "other",
    "object",
    "other",
    "other",
    "other",
    "other",
    "other",
    "other",
    "other",
    "other",
    "other",
    "other",
    "object",
    "other",
    "other",
    "other",
    "other",
    "other",
    "other",
    "other",
    "other",
    "other",
    "other",
    "other",
    "other",
    "other",
    "other",
    "other",
    "other",
    "other",
    "other",
    "other",
    "other",
    "other",
    "other",
    "hallu",
    "hallu",
    "other",
    "other",
    "other",
    "other",
    "other",
    "other",
    "other",
    "other",
    "other",
    "other",
    "hallu",
    "hallu",
    "hallu",
    "other",
    "other",
    "other",
    "object",
    "other",
    "other",
    "other",
    "other",
    "other",
    "other",
    "other",
    "other",
    "other",
    "object",
    "other",
    "other",
    "other",
    "other",
    "other",
    "other",
    "other",
    "other",
    "other",
    "object",
    "other",
    "other",
    "other",
    "other",
    "other",
    "other",
    "other",
    "other",
    "other",
    "other",
    "other",
    "other",
    "other",
    "other",
    "other",
    "other",
    "other",
    "other"
  ],
  "soft_scales": [
    0.4,
    0.4,
    0.4,
    0.4,
    0.4,
    0.4,
    0.4,
    0.4,
    0.4,
    0.4,
    0.8,
    0.4,
    0.4,
    0.4,
    0.4,
    0.4,
    0.4,
    0.8,
    0.4,
    0.4,
    0.4,
    0.4,
    0.4,
    0.4,
    0.4,
    0.4,
    0.4,
    0.4,
    0.8,
    0.4,
    0.4,
    0.4,
    0.4,
    0.4,
    0.4,
    0.4,
    0.4,
    0.4,
    0.4,
    0.4,
    0.4,
    0.4,
    0.4,
    0.4,
    0.4,
    0.4,
    0.4,
    0.4,
    0.4,
    0.4,
    0.4,
    0.8,
    0.8,
    0.4,
    0.4,
    0.4,
    0.4,
    0.4,
    0.4,
    0.4,
    0.4,
    0.4,
    0.4,
    0.8,
    0.8,
    0.8,
    0.4,
    0.4,
    0.4,
    0.8,
    0.4,
    0.4,
    0.4,
    0.4,
    0.4,
    0.4,
    0.4,
    0.4,
    0.4,
    0.8,
    0.4,
    0.4,
    0.4,
    0.4,
    0.4,
    0.4,
    0.4,
    0.4,
    0.4,
    0.8,
    0.4,
    0.4,
    0.4,
    0.4,
    0.4,
    0.4,
    0.4,
    0.4,
    0.4,
    0.4,
    0.4,
    0.4,
    0.4,
    0.4,
    0.4,
    0.4,
    0.4,
    0.4
  ],
  "trace": {
    "logprob_v": [
      -0.24581065773963928,
      -0.12201906740665436,
      -1.1110107898712158,
      -0.6498881578445435,
      -1.6527431011199951,
      -0.18926551938056946,
      -0.13768282532691956,
      -0.31790104508399963,
      -0.7060412764549255,
      -1.2365329265594482,
      -0.5558609366416931,
      -0.47817283868789673,
      -1.2402982711791992,
      -0.2751791179180145,
      -1.1123619079589844,
      -0.7733311057090759,
      -0.13866542279720306,
      -0.15281109511852264,
      -0.2657221257686615,
      -1.5881445407867432,
      -1.4174565076828003,
      -0.0847344696521759,
      -0.3209979236125946,
      -0.0003978414461016655,
      -0.27958571910858154,
      -0.5786525011062622,
      -0.15977022051811218,
      -0.034683771431446075,
      -0.2861115038394928,
      -0.28768908977508545,
      -1.9288547039031982,
      -0.00034528967808000743,
      -1.0742485523223877,
      -0.7369937896728516,
      -0.17918704450130463,
      -0.4805474281311035,
      -1.0982325077056885,
      -0.958159327507019,
      -0.5986577272415161,
      -1.6991132497787476,
      -4.6491513785440475e-06,
      -0.43137112259864807,
      -0.10824856162071228,
      -0.7360547184944153,
      -0.020794708281755447,
      0.0,
      -0.7919210195541382,
      -1.3736977577209473,
      -1.7165336608886719,
      -0.6982146501541138,
      -0.45062774419784546,
      -0.7111096978187561,
      -0.0021401375997811556,
      -1.4266741275787354,
      -0.5014532208442688,
      -0.0003660247311927378,
      -1.1986958980560303,
      -0.1934923678636551,
      -1.138057827949524,
      -0.001585775287821889,
      -0.4425521790981293,
      -0.5082770586013794,
      -0.3728744387626648,
      -1.5042650699615479,
      -0.02602405473589897,
      -0.9962835907936096,
      -1.3701318502426147,
      -1.340433120727539,
      -0.004119838587939739,
      -0.5638454556465149,
      -0.6442220211029053,
      -2.3243966102600098,
      -0.1311076134443283,
      -0.0040093050338327885,
      -0.3396969735622406,
      -0.01780444197356701,
      -0.08336656540632248,
      -0.14779619872570038,
      -0.5926411151885986,
      -0.5082942247390747,
      -1.1419107913970947,
      -1.7895328998565674,
      -0.4773256480693817,
      -0.6648330092430115,
      -0.0023252135142683983,
      -0.1690332591533661,
      -0.02633853256702423,
      -0.8314580321311951,
      -0.2689904272556305,
      -1.1116909980773926,
      -1.6574392318725586,
      -0.0015244778478518128,
      -0.052474495023489,
      -0.31862449645996094,
      -0.2150898575782776,
      -0.4327836334705353,
      -0.34729546308517456,
      -0.0004764852055814117,
      -0.4405435621738434,
      -0.013650169596076012,
      -4.327203714638017e-05,
      -0.0203692764043808,
      -0.05450692027807236,
      -1.0050981044769287,
      -0.00020752183627337217,
      -0.026502234861254692,
      -0.0960269346833229,
      -0.6263627409934998
    ],
    "logprob_g": [
      -0.25370293855667114,
      -0.12274422496557236,
      -1.1994459629058838,
      -0.6769647598266602,
      -2.043104648590088,
      -0.050990231335163116,
      -0.10832986235618591,
      -0.3980623781681061,
      -0.6254683136940002,
      -1.355363130569458,
      -0.4854499399662018,
      -0.43265509605407715,
      -1.436335802078247,
      -0.22386370599269867,
      -1.1376103162765503,
      -0.7500907182693481,
      -0.10994540899991989,
      -0.14262764155864716,
      -0.1864163875579834,
      -1.9927468299865723,
      -1.6970465183258057,
      -0.08644727617502213,
      -0.4786015748977661,
      -0.0006962973857298493,
      -0.20731109380722046,
      -0.48086345195770264,
      -0.233623206615448,
      -0.06757992506027222,
      -0.2797645330429077,
      -0.32460159063339233,
      -2.2993671894073486,
      -0.0013324677711352706,
      -1.1697434186935425,
      -1.039078950881958,
      -0.19021381437778473,
      -0.2914932370185852,
      -1.6726925373077393,
      -1.2006953954696655,
      -0.4507485032081604,
      -1.3968117237091064,
      -0.0011038646334782243,
      -0.489865243434906,
      -0.1344747692346573,
      -0.7975549101829529,
      -0.04759606346487999,
      -1.1920928244535389e-07,
      -0.7394988536834717,
      -1.579545259475708,
      -1.4895447492599487,
      -0.6943560838699341,
      -0.4780082404613495,
      -0.8669300079345703,
      -0.001980012049898505,
      -0.9790412187576294,
      -0.585743248462677,
      -0.0003165697562508285,
      -1.3390878438949585,
      -0.28834983706474304,
      -1.1903597116470337,
      -0.0025648337323218584,
      -0.45399391651153564,
      -0.5331597328186035,
      -0.48402369022369385,
      -1.129730463027954,
      -0.0060799880884587765,
      -1.6516237258911133,
      -1.4105515480041504,
      -1.1150424480438232,
      -0.003907783888280392,
      -0.5145537257194519,
      -0.40256690979003906,
      -2.789548635482788,
      -0.20048515498638153,
      -0.002827339107170701,
      -0.3525049686431885,
      -0.019836734980344772,
      -0.13837262988090515,
      -0.21704964339733124,
      -0.7923387885093689,
      -0.5633544921875,
      -1.0468401908874512,
      -1.8277980089187622,
      -0.6932213306427002,
      -0.9077155590057373,
      -0.004222762770950794,
      -0.12302834540605545,
      -0.028746316209435463,
      -0.7804309725761414,
      -0.5323140025138855,
      -0.8210710883140564,
      -2.2742116451263428,
      -0.004638150800019503,
      -0.11587981134653091,
      -0.23422758281230927,
      -0.389371782541275,
      -0.4096355736255646,
      -0.37750300765037537,
      -0.000579546787776053,
      -0.49434560537338257,
      -0.03633003309369087,
      -0.00023624490131624043,
      -0.053956903517246246,
      -0.06108766421675682,
      -1.4215350151062012,
      -0.0003516055876389146,
      -0.061082616448402405,
      -0.06567440181970596,
      -0.5748189687728882
    ],
    "logprob_s": [
      -0.24417275190353394,
      -0.12033118307590485,
      -1.1461904048919678,
      -0.6697861552238464,
      -1.8060717582702637,
      -0.12303024530410767,
      -0.12420212477445602,
      -0.35031014680862427,
      -0.6662362813949585,
      -1.2515453100204468,
      -0.5055203437805176,
      -0.4415343105792999,
      -1.3062784671783447,
      -0.2569299638271332,
      -1.1176337003707886,
      -0.7320191264152527,
      -0.11804642528295517,
      -0.1460677683353424,
      -0.2261532098054886,
      -1.7296733856201172,
      -1.4893794059753418,
      -0.08274177461862564,
      -0.36597922444343567,
      -0.0004530118894763291,
      -0.26042190194129944,
      -0.5845314264297485,
      -0.1881587952375412,
      -0.04927103966474533,
      -0.2968847453594208,
      -0.2938610315322876,
      -2.030855655670166,
      -0.000474936212413013,
      -1.08818781375885,
      -0.8213468790054321,
      -0.17120566964149475,
      -0.4063304364681244,
      -1.2709017992019653,
      -1.0921525955200195,
      -0.5305166244506836,
      -1.4440205097198486,
      -2.455681169521995e-05,
      -0.429121196269989,
      -0.12044373899698257,
      -0.7566822171211243,
      -0.028183797374367714,
      0.0,
      -0.7758827209472656,
      -1.4469274282455444,
      -1.6487839221954346,
      -0.7155062556266785,
      -0.438568651676178,
      -0.756321370601654,
      -0.0023316359147429466,
      -1.3834818601608276,
      -0.47766923904418945,
      -0.0003280101518612355,
      -1.2273337841033936,
      -0.23237727582454681,
      -1.189575433731079,
      -0.0017220443114638329,
      -0.43737882375717163,
      -0.4987022876739502,
      -0.36563897132873535,
      -1.3125331401824951,
      -0.014069301076233387,
      -1.243958592414856,
      -1.4516655206680298,
      -1.2005293369293213,
      -0.00386040355078876,
      -0.5751431584358215,
      -0.5841166973114014,
      -2.499145984649658,
      -0.15085187554359436,
      -0.0025908732786774635,
      -0.324733167886734,
      -0.019734470173716545,
      -0.09192457050085068,
      -0.1668170690536499,
      -0.6741895079612732,
      -0.5792976021766663,
      -1.1687445640563965,
      -1.7306404113769531,
      -0.555525541305542,
      -0.724575936794281,
      -0.002641167026013136,
      -0.14834855496883392,
      -0.024362703785300255,
      -0.9015183448791504,
      -0.34923532605171204,
      -0.9641869068145752,
      -1.8948676586151123,
      -0.0022527810651808977,
      -0.07192052900791168,
      -0.26047828793525696,
      -0.275404155254364,
      -0.41480132937431335,
      -0.35329684615135193,
      -0.0004847066884394735,
      -0.4624249339103699,
      -0.01546709518879652,
      -7.56950321374461e-05,
      -0.02709284983575344,
      -0.0555911585688591,
      -1.1025595664978027,
      -0.00022825974156148732,
      -0.03469793498516083,
      -0.06735283136367798,
      -0.6759634613990784
    ],
    "entropy_v": [
      0.6525613069534302,
      0.3729773759841919,
      1.7229104042053223,
      1.1652272939682007,
      2.725303888320923,
      0.47380948066711426,
      0.5292462110519409,
      0.9003571271896362,
      1.199272632598877,
      1.7938666343688965,
      1.3365877866744995,
      1.7706812620162964,
      2.3488869667053223,
      1.0742415189743042,
      1.6781591176986694,
      1.6647899150848389,
      0.40454548597335815,
      0.5302218794822693,
      0.8152029514312744,
      3.351241111755371,
      2.464503288269043,
      0.3420901298522949,
      0.8439366817474365,
      0.004325497895479202,
      1.100541353225708,
      2.156670093536377,
      0.5350492000579834,
      0.18367233872413635,
      0.9330798983573914,
      1.000159740447998,
      3.0402302742004395,
      0.003832900431007147,
      1.9587287902832031,
      1.4951176643371582,
      0.7111031413078308,
      1.2088897228240967,
      2.1503965854644775,
      1.4234286546707153,
      2.2922728061676025,
      3.5234572887420654,
      6.84398110024631e-05,
      1.169252872467041,
      0.43149760365486145,
      1.7073413133621216,
      0.11672522127628326,
      1.0887063126574503e-06,
      1.7465567588806152,
      3.0327835083007812,
      3.2828762531280518,
      1.9951149225234985,
      1.388619065284729,
      2.2061007022857666,
      0.019423985853791237,
      3.3308844566345215,
      1.2623205184936523,
      0.004029061645269394,
      2.3012049198150635,
      0.6166096925735474,
      2.0835282802581787,
      0.016435356810688972,
      1.198036789894104,
      0.8796260356903076,
      0.8622331619262695,
      3.3835391998291016,
      0.1475440412759781,
      3.2362782955169678,
      2.775535821914673,
      1.9830718040466309,
      0.03427351266145706,
      1.2626357078552246,
      1.5012178421020508,
      3.2817773818969727,
      0.6065865755081177,
      0.02732696197926998,
      1.2189315557479858,
      0.10343267768621445,
      0.44652318954467773,
      0.5060803294181824,
      1.8055188655853271,
      2.08219575881958,
      1.7053228616714478,
      3.538036584854126,
      1.009804368019104,
      1.6958197355270386,
      0.02039261907339096,
      0.6852518916130066,
      0.18609747290611267,
      2.5736804008483887,
      0.9473961591720581,
      2.4774062633514404,
      2.657888412475586,
      0.01475144550204277,
      0.25773730874061584,
      0.748018741607666,
      0.7071973085403442,
      0.9534690380096436,
      1.3508951663970947,
      0.005130486097186804,
      0.7300119996070862,
      0.10009775310754776,
      0.0006294730701483786,
      0.11377213150262833,
      0.23280201852321625,
      1.6274704933166504,
      0.0022435178980231285,
      0.12812292575836182,
      0.3630704879760742,
      1.0046571493148804
    ],
    "entropy_g": [
      0.677031934261322,
      0.37841206789016724,
      1.7557196617126465,
      1.2281594276428223,
      2.7484629154205322,
      0.2092697024345398,
      0.4680204689502716,
      0.9420265555381775,
      1.1774775981903076,
      1.7848098278045654,
      1.2722235918045044,
      1.6840649843215942,
      2.434556007385254,
      0.9181712865829468,
      1.7464969158172607,
      1.7224688529968262,
      0.3641398847103119,
      0.49178487062454224,
      0.7131209373474121,
      3.556711196899414,
      2.4882383346557617,
      0.34902605414390564,
      0.9405733346939087,
      0.00697293458506465,
      0.9076883792877197,
      1.8450610637664795,
      0.7019104361534119,
      0.302365779876709,
      0.968467116355896,
      1.1037366390228271,
      3.2516226768493652,
      0.010803756304085255,
      2.133587121963501,
      1.8498611450195312,
      0.7917052507400513,
      0.9673699140548706,
      2.5225820541381836,
      1.4626095294952393,
      1.92245614528656,
      3.22196102142334,
      0.009430039674043655,
      1.2102314233779907,
      0.4893976151943207,
      1.6640338897705078,
      0.2165774405002594,
      3.782701469390304e-06,
      1.6576708555221558,
      3.1663737297058105,
      3.2560811042785645,
      2.113398790359497,
      1.455682635307312,
      2.2188124656677246,
      0.017998872324824333,
      2.8615541458129883,
      1.4732043743133545,
      0.003686592448502779,
      2.3659183979034424,
      0.7681616544723511,
      2.1292474269866943,
      0.024562805891036987,
      1.2283393144607544,
      0.8661143779754639,
      0.9517095685005188,
      3.047462224960327,
      0.04590461030602455,
      3.6143856048583984,
      2.907944679260254,
      1.9436360597610474,
      0.0322873629629612,
      1.2404510974884033,
      1.3472628593444824,
      3.2517049312591553,
      0.7959825396537781,
      0.022334881126880646,
      1.3029990196228027,
      0.11250737309455872,
      0.6643722057342529,
      0.6887208819389343,
      2.0990967750549316,
      2.206571578979492,
      1.7553479671478271,
      3.5333781242370605,
      1.251485824584961,
      1.8831064701080322,
      0.0342845693230629,
      0.6140619516372681,
      0.2033512443304062,
      2.53305721282959,
      1.3706614971160889,
      2.3457746505737305,
      2.864673614501953,
      0.038495391607284546,
      0.47124189138412476,
      0.7412558794021606,
      0.9846885204315186,
      0.9727461934089661,
      1.3870265483856201,
      0.006071270909160376,
      0.8605451583862305,
      0.21483401954174042,
      0.0029166569001972675,
      0.2586914598941803,
      0.2700499892234802,
      1.9215067625045776,
      0.0037382226437330246,
      0.2489413619041443,
      0.29824453592300415,
      1.0188668966293335
    ],
    "entropy_s": [
      0.6558820009231567,
      0.37011805176734924,
      1.7297677993774414,
      1.1849045753479004,
      2.724996566772461,
      0.3711574971675873,
      0.4991741180419922,
      0.9114118218421936,
      1.1643177270889282,
      1.7760592699050903,
      1.2737789154052734,
      1.6929404735565186,
      2.371229410171509,
      1.0195932388305664,
      1.6909929513931274,
      1.663424015045166,
      0.37147319316864014,
      0.5034560561180115,
      0.7679737210273743,
      3.445019006729126,
      2.4840385913848877,
      0.34221017360687256,
      0.879804790019989,
      0.0048461356200277805,
      1.056772232055664,
      2.137521982192993,
      0.5998480916023254,
      0.23878532648086548,
      0.9690831303596497,
      1.018578290939331,
      3.108269214630127,
      0.004760987590998411,
      2.001713752746582,
      1.6152702569961548,
      0.7032131552696228,
      1.1390197277069092,
      2.292635917663574,
      1.4481542110443115,
      2.105534076690674,
      3.3176889419555664,
      0.00030680999043397605,
      1.1489390134811401,
      0.4558945298194885,
      1.6874103546142578,
      0.14714807271957397,
      8.949356811172038e-07,
      1.7104506492614746,
      3.0842480659484863,
      3.3253605365753174,
      2.02079176902771,
      1.3587720394134521,
      2.1944422721862793,
      0.021020030602812767,
      3.3064041137695312,
      1.2358980178833008,
      0.0037252968177199364,
      2.3059029579162598,
      0.6761125326156616,
      2.107132911682129,
      0.017318736761808395,
      1.1753591299057007,
      0.8765747547149658,
      0.8716702461242676,
      3.1891400814056396,
      0.09096550196409225,
      3.468850612640381,
      2.8027992248535156,
      1.942786455154419,
      0.0322079099714756,
      1.2829663753509521,
      1.4612712860107422,
      3.2783589363098145,
      0.6631563901901245,
      0.01943698339164257,
      1.1995141506195068,
      0.11096368730068207,
      0.4824230968952179,
      0.5524940490722656,
      1.9012857675552368,
      2.228330135345459,
      1.7172904014587402,
      3.543443441390991,
      1.099793553352356,
      1.7305200099945068,
      0.022816382348537445,
      0.6419364213943481,
      0.17399878799915314,
      2.671004295349121,
      1.1169018745422363,
      2.4274396896362305,
      2.722238779067993,
      0.02066662535071373,
      0.32939326763153076,
      0.7185567617416382,
      0.8110231161117554,
      0.9310960173606873,
      1.344609022140503,
      0.005177623592317104,
      0.7648995518684387,
      0.10978848487138748,
      0.0010390901006758213,
      0.14548403024673462,
      0.2414644956588745,
      1.6854736804962158,
      0.0024659496266394854,
      0.15929749608039856,
      0.2890182137489319,
      1.0115203857421875
    ]
  },
  "stats": {
    "counts": {
      "hallu": 5,
      "object": 6,
      "len": 108
    },
    "delta_nll_global": {
      "mean_hallu": 0.08330432930961251,
      "count_hallu": 5,
      "mean_object": -0.0619654655456543,
      "count_object": 6,
      "mean_other": 0.048605419146305014,
      "count_other": 97
    },
    "delta_nll_soft": {
      "mean_hallu": 0.01787829785607755,
      "count_hallu": 5,
      "mean_object": -0.01858561486005783,
      "count_object": 6,
      "mean_other": 0.013555789553776645,
      "count_other": 97
    },
    "delta_entropy_global": {
      "mean_hallu": -0.009664490073919296,
      "count_hallu": 5,
      "mean_object": -0.01614239811897278,
      "count_object": 6,
      "mean_other": 0.040776020061448155,
      "count_other": 97
    },
    "delta_entropy_soft": {
      "mean_hallu": -0.005693545192480087,
      "count_hallu": 5,
      "mean_object": 0.010487834612528482,
      "count_object": 6,
      "mean_other": 0.007470740179724441,
      "count_other": 97
    }
  },
  "meta": {
    "lambda_global": 1.0,
    "lam_other": 0.4,
    "lam_object": 0.8,
    "lam_hallu": 0.8,
    "sim_threshold": 0.8
  }
}