{
  "id": 926,
  "image_file": "AMBER_926.jpg",
  "query_text": "Describe this image.",
  "response": "The image features two people in a small boat, paddling across a large body of water. The boat is positioned in the middle of the scene, with one person on the left side and the other on the right side. The two individuals are focused on their journey, navigating through the water.\n\nThe scene is set against a backdrop of a clear blue sky, which adds to the serene atmosphere of the image. The boat appears to be a canoe, and the two people seem to be enjoying their time on the water.",
  "token_ids": [
    450,
    1967,
    5680,
    1023,
    2305,
    297,
    263,
    2319,
    13006,
    29892,
    282,
    1202,
    1847,
    4822,
    263,
    2919,
    3573,
    310,
    4094,
    29889,
    450,
    13006,
    338,
    2602,
    287,
    297,
    278,
    7256,
    310,
    278,
    9088,
    29892,
    411,
    697,
    2022,
    373,
    278,
    2175,
    2625,
    322,
    278,
    916,
    373,
    278,
    1492,
    2625,
    29889,
    450,
    1023,
    15724,
    526,
    21309,
    373,
    1009,
    16342,
    29892,
    12402,
    1218,
    1549,
    278,
    4094,
    29889,
    13,
    13,
    1576,
    9088,
    338,
    731,
    2750,
    263,
    1250,
    8865,
    310,
    263,
    2821,
    7254,
    14744,
    29892,
    607,
    12778,
    304,
    278,
    724,
    1600,
    25005,
    310,
    278,
    1967,
    29889,
    450,
    13006,
    5692,
    304,
    367,
    263,
    508,
    7297,
    29892,
    322,
    278,
    1023,
    2305,
    2833,
    304,
    367,
    11418,
    5414,
    1009,
    931,
    373,
    278,
    4094,
    29889
  ],
  "tokens": [
    "The",
    "image",
    "features",
    "two",
    "people",
    "in",
    "a",
    "small",
    "boat",
    ",",
    "p",
    "add",
    "ling",
    "across",
    "a",
    "large",
    "body",
    "of",
    "water",
    ".",
    "The",
    "boat",
    "is",
    "position",
    "ed",
    "in",
    "the",
    "middle",
    "of",
    "the",
    "scene",
    ",",
    "with",
    "one",
    "person",
    "on",
    "the",
    "left",
    "side",
    "and",
    "the",
    "other",
    "on",
    "the",
    "right",
    "side",
    ".",
    "The",
    "two",
    "individuals",
    "are",
    "focused",
    "on",
    "their",
    "journey",
    ",",
    "navig",
    "ating",
    "through",
    "the",
    "water",
    ".",
    "\n",
    "\n",
    "The",
    "scene",
    "is",
    "set",
    "against",
    "a",
    "back",
    "drop",
    "of",
    "a",
    "clear",
    "blue",
    "sky",
    ",",
    "which",
    "adds",
    "to",
    "the",
    "ser",
    "ene",
    "atmosphere",
    "of",
    "the",
    "image",
    ".",
    "The",
    "boat",
    "appears",
    "to",
    "be",
    "a",
    "can",
    "oe",
    ",",
    "and",
    "the",
    "two",
    "people",
    "seem",
    "to",
    "be",
    "enjo",
    "ying",
    "their",
    "time",
    "on",
    "the",
    "water",
    "."
  ],
  "token_types": [
    "other",
    "other",
    "other",
    "other",
    "object",
    "other",
    "other",
    "other",
    "hallu",
    "other",
    "other",
    "other",
    "other",
    "other",
    "other",
    "other",
    "other",
    "other",
    "object",
    "other",
    "other",
    "hallu",
    "other",
    "other",
    "other",
    "other",
    "other",
    "other",
    "other",
    "other",
    "other",
    "other",
    "other",
    "other",
    "object",
    "other",
    "other",
    "other",
    "other",
    "other",
    "other",
    "other",
    "other",
    "other",
    "other",
    "other",
    "other",
    "other",
    "other",
    "other",
    "other",
    "other",
    "other",
    "other",
    "other",
    "other",
    "other",
    "other",
    "other",
    "other",
    "object",
    "other",
    "other",
    "other",
    "other",
    "other",
    "other",
    "other",
    "other",
    "other",
    "other",
    "other",
    "other",
    "other",
    "other",
    "other",
    "object",
    "other",
    "other",
    "other",
    "other",
    "other",
    "other",
    "other",
    "other",
    "other",
    "other",
    "other",
    "other",
    "other",
    "hallu",
    "other",
    "other",
    "other",
    "other",
    "other",
    "other",
    "other",
    "other",
    "other",
    "other",
    "object",
    "other",
    "other",
    "other",
    "other",
    "other",
    "other",
    "other",
    "other",
    "other",
    "object",
    "other"
  ],
  "soft_scales": [
    0.3,
    0.3,
    0.3,
    0.3,
    0.9,
    0.3,
    0.3,
    0.3,
    0.9,
    0.3,
    0.3,
    0.3,
    0.3,
    0.3,
    0.3,
    0.3,
    0.3,
    0.3,
    0.9,
    0.3,
    0.3,
    0.9,
    0.3,
    0.3,
    0.3,
    0.3,
    0.3,
    0.3,
    0.3,
    0.3,
    0.3,
    0.3,
    0.3,
    0.3,
    0.9,
    0.3,
    0.3,
    0.3,
    0.3,
    0.3,
    0.3,
    0.3,
    0.3,
    0.3,
    0.3,
    0.3,
    0.3,
    0.3,
    0.3,
    0.3,
    0.3,
    0.3,
    0.3,
    0.3,
    0.3,
    0.3,
    0.3,
    0.3,
    0.3,
    0.3,
    0.9,
    0.3,
    0.3,
    0.3,
    0.3,
    0.3,
    0.3,
    0.3,
    0.3,
    0.3,
    0.3,
    0.3,
    0.3,
    0.3,
    0.3,
    0.3,
    0.9,
    0.3,
    0.3,
    0.3,
    0.3,
    0.3,
    0.3,
    0.3,
    0.3,
    0.3,
    0.3,
    0.3,
    0.3,
    0.3,
    0.9,
    0.3,
    0.3,
    0.3,
    0.3,
    0.3,
    0.3,
    0.3,
    0.3,
    0.3,
    0.3,
    0.9,
    0.3,
    0.3,
    0.3,
    0.3,
    0.3,
    0.3,
    0.3,
    0.3,
    0.3,
    0.9,
    0.3
  ],
  "trace": {
    "logprob_v": [
      -0.21717140078544617,
      -0.09087871015071869,
      -0.973574161529541,
      -0.694974422454834,
      -0.10253617912530899,
      -1.2740389108657837,
      -0.04758412763476372,
      -0.4936436414718628,
      -0.516223132610321,
      -1.0190131664276123,
      -1.0251340866088867,
      -0.006475774105638266,
      -0.0020632902160286903,
      -1.1838585138320923,
      -0.2524452209472656,
      -0.7486802935600281,
      -0.10697019845247269,
      -4.3987260141875595e-05,
      -0.08168648183345795,
      -0.7471588850021362,
      -0.7804585099220276,
      -0.2778994143009186,
      -0.46897798776626587,
      -1.5280158519744873,
      -4.100715523236431e-05,
      -0.6922658681869507,
      -0.012339912354946136,
      -0.4904378056526184,
      -0.024840164929628372,
      -0.032492686063051224,
      -0.3780055046081543,
      -0.21084460616111755,
      -0.5937719941139221,
      -0.8818918466567993,
      -0.0893324464559555,
      -1.204293131828308,
      -0.13569307327270508,
      -0.053708385676145554,
      -0.11748407036066055,
      -0.14304524660110474,
      -0.10212337225675583,
      -0.010102802887558937,
      -0.4387316107749939,
      -0.00024911639047786593,
      -0.000740968796890229,
      -0.2963579595088959,
      -0.3186274468898773,
      -0.9357597827911377,
      -1.7495613098144531,
      -0.5410435199737549,
      -0.8605719804763794,
      -1.8801071643829346,
      -0.03718551620841026,
      -0.914277970790863,
      -1.1658868789672852,
      -0.323824405670166,
      -1.0371626615524292,
      -0.00015162272029556334,
      -0.6951706409454346,
      -0.022704528644680977,
      -1.204337239265442,
      -1.265215516090393,
      -0.496108740568161,
      -0.00011526874004630372,
      -0.39099258184432983,
      -2.1186282634735107,
      -1.2789576053619385,
      -1.1274561882019043,
      -0.3359495997428894,
      -0.07504549622535706,
      -0.9333430528640747,
      -0.00019941726350225508,
      -0.011062008328735828,
      -0.5722963809967041,
      -1.094693660736084,
      -0.48769116401672363,
      -0.014309766702353954,
      -0.12235508114099503,
      -1.3730491399765015,
      -1.2795199155807495,
      -0.4574480354785919,
      -0.00187923654448241,
      -0.9421249628067017,
      -0.23654893040657043,
      -0.5220181345939636,
      -0.41308706998825073,
      -0.04775837063789368,
      -0.703274667263031,
      -0.007206754293292761,
      -0.3767085671424866,
      -1.7601583003997803,
      -1.1079297065734863,
      -0.10722960531711578,
      -0.0258835069835186,
      -1.1116584539413452,
      -0.7376406192779541,
      -0.0003743662964552641,
      -0.3768569231033325,
      -1.2431668043136597,
      -0.463583767414093,
      -1.0861707925796509,
      -0.4402485489845276,
      -0.9919338226318359,
      -0.06324849277734756,
      -0.019722899422049522,
      -0.10663476586341858,
      -7.986990567587782e-06,
      -0.2030659019947052,
      -0.04640866070985794,
      -0.8902445435523987,
      -0.010532152839004993,
      -0.04119999706745148,
      -0.6091079711914062
    ],
    "logprob_g": [
      -0.23142747581005096,
      -0.0940171331167221,
      -1.0852357149124146,
      -0.6883544325828552,
      -0.07365661859512329,
      -1.0689890384674072,
      -0.04920420050621033,
      -0.7069094181060791,
      -0.5320591926574707,
      -1.0538264513015747,
      -0.9732413291931152,
      -0.009805725887417793,
      -0.0012759171659126878,
      -1.4261882305145264,
      -0.35588741302490234,
      -0.6618579626083374,
      -0.07142817974090576,
      -9.464769391342998e-05,
      -0.07140398025512695,
      -0.522079586982727,
      -0.5765361785888672,
      -0.3805692493915558,
      -0.4869491755962372,
      -1.720435619354248,
      -0.00010132275929208845,
      -0.7702580690383911,
      -0.020769372582435608,
      -0.5515190958976746,
      -0.029001576825976372,
      -0.018166232854127884,
      -0.41451290249824524,
      -0.13198606669902802,
      -0.6382260322570801,
      -1.095127820968628,
      -0.1552937924861908,
      -1.2354509830474854,
      -0.21974508464336395,
      -0.1467505842447281,
      -0.07726281136274338,
      -0.1871892660856247,
      -0.13871097564697266,
      -0.006779762916266918,
      -0.5546261072158813,
      -0.00028761065914295614,
      -0.00243105785921216,
      -0.13547250628471375,
      -0.27577969431877136,
      -0.9037044048309326,
      -1.455560564994812,
      -0.7372510433197021,
      -0.7985667586326599,
      -1.999013900756836,
      -0.02441982366144657,
      -0.9994444251060486,
      -2.9027342796325684,
      -0.3130373954772949,
      -1.2635992765426636,
      -0.00020668754586949944,
      -0.9357860684394836,
      -0.029307015240192413,
      -1.2226667404174805,
      -0.9044640064239502,
      -0.7882424592971802,
      -0.002580647822469473,
      -0.49486181139945984,
      -2.2735002040863037,
      -1.4216967821121216,
      -0.7704257965087891,
      -0.5552873611450195,
      -0.07833512872457504,
      -1.6397489309310913,
      -0.0007279845303855836,
      -0.029126055538654327,
      -0.5328294634819031,
      -1.0032075643539429,
      -0.48258429765701294,
      -0.009134644642472267,
      -0.08242182433605194,
      -1.392971158027649,
      -1.2903790473937988,
      -0.5702558159828186,
      -0.0020342625211924314,
      -1.2636847496032715,
      -0.5591534376144409,
      -0.9001697897911072,
      -0.21587489545345306,
      -0.07705125957727432,
      -0.41855815052986145,
      -0.020210642367601395,
      -0.36686593294143677,
      -2.2764923572540283,
      -1.302473783493042,
      -0.14353899657726288,
      -0.025282297283411026,
      -1.9405415058135986,
      -0.8748030662536621,
      -0.000704278820194304,
      -0.3250495493412018,
      -1.3711353540420532,
      -0.5594900846481323,
      -1.0165045261383057,
      -0.31249183416366577,
      -1.3264641761779785,
      -0.08353303372859955,
      -0.011837593279778957,
      -0.19536320865154266,
      -0.0012919898144900799,
      -0.4159357249736786,
      -0.08212065696716309,
      -0.7601210474967957,
      -0.011242847889661789,
      -0.07048308104276657,
      -0.843300461769104
    ],
    "logprob_s": [
      -0.22172462940216064,
      -0.09087729454040527,
      -1.005980134010315,
      -0.6810256838798523,
      -0.07835717499256134,
      -1.1895033121109009,
      -0.04769790545105934,
      -0.5480391383171082,
      -0.5523703694343567,
      -1.0228347778320312,
      -0.9926210641860962,
      -0.007352318149060011,
      -0.0016526625258848071,
      -1.2353209257125854,
      -0.2707960307598114,
      -0.712591290473938,
      -0.09249996393918991,
      -5.2927523938706145e-05,
      -0.07834317535161972,
      -0.6521847248077393,
      -0.681832492351532,
      -0.26975932717323303,
      -0.4698885977268219,
      -1.566662073135376,
      -5.602679812000133e-05,
      -0.7067918181419373,
      -0.013155097141861916,
      -0.4943554103374481,
      -0.026246916502714157,
      -0.02631019987165928,
      -0.3721446692943573,
      -0.18303152918815613,
      -0.5734519362449646,
      -0.9379801154136658,
      -0.12192198634147644,
      -1.1555966138839722,
      -0.16952067613601685,
      -0.072602778673172,
      -0.09758775681257248,
      -0.15042223036289215,
      -0.11839912831783295,
      -0.009535245597362518,
      -0.5311093330383301,
      -0.00025650550378486514,
      -0.0010656398953869939,
      -0.2344256341457367,
      -0.31126245856285095,
      -1.052329659461975,
      -1.5595041513442993,
      -0.5894105434417725,
      -0.8423941731452942,
      -1.8194612264633179,
      -0.033149201422929764,
      -0.9746115207672119,
      -1.4094465970993042,
      -0.30642932653427124,
      -1.0357248783111572,
      -0.00016330339713022113,
      -0.7435428500175476,
      -0.021511100232601166,
      -1.1463253498077393,
      -1.1721493005752563,
      -0.47920629382133484,
      -7.247662142617628e-05,
      -0.41748133301734924,
      -2.184380054473877,
      -1.3089531660079956,
      -1.0652387142181396,
      -0.37914419174194336,
      -0.0738070011138916,
      -1.059044361114502,
      -0.00023934361524879932,
      -0.014380978420376778,
      -0.5792264342308044,
      -1.0495432615280151,
      -0.4911680221557617,
      -0.011287285946309566,
      -0.1026088073849678,
      -1.334780216217041,
      -1.2149677276611328,
      -0.4848303198814392,
      -0.0017995130037888885,
      -1.0489119291305542,
      -0.29465624690055847,
      -0.5965076684951782,
      -0.3433440625667572,
      -0.05176376923918724,
      -0.5400988459587097,
      -0.009517178870737553,
      -0.3507888913154602,
      -1.768641471862793,
      -1.147313117980957,
      -0.11907940357923508,
      -0.026007911190390587,
      -1.3562943935394287,
      -0.8065829277038574,
      -0.0004524161049630493,
      -0.3563854396343231,
      -1.2413166761398315,
      -0.48680537939071655,
      -1.0792484283447266,
      -0.3332464098930359,
      -1.0871334075927734,
      -0.06172388419508934,
      -0.016687333583831787,
      -0.11194746196269989,
      -1.7523612768854946e-05,
      -0.22547267377376556,
      -0.047927919775247574,
      -0.8718562126159668,
      -0.009685547091066837,
      -0.057454414665699005,
      -0.6448996067047119
    ],
    "entropy_v": [
      0.646796703338623,
      0.3106343448162079,
      1.733765721321106,
      0.8321390151977539,
      0.5714923143386841,
      2.270862340927124,
      0.3054690659046173,
      1.65725576877594,
      1.6892142295837402,
      2.2284326553344727,
      2.8505215644836426,
      0.04070572555065155,
      0.016647078096866608,
      2.3102946281433105,
      0.7744399309158325,
      1.8585360050201416,
      0.5371977686882019,
      0.0005581025034189224,
      0.4233058989048004,
      1.5555909872055054,
      1.1890615224838257,
      1.40622878074646,
      1.345682978630066,
      3.4335155487060547,
      0.0005450469325296581,
      2.1643478870391846,
      0.08903885632753372,
      0.93539959192276,
      0.15556347370147705,
      0.15854258835315704,
      1.2827749252319336,
      0.7211660742759705,
      1.7478444576263428,
      1.4893834590911865,
      0.43602877855300903,
      2.6729233264923096,
      0.4879775643348694,
      0.28842294216156006,
      0.4337240755558014,
      0.5824396014213562,
      0.3308621048927307,
      0.057765331119298935,
      1.0007275342941284,
      0.002657155506312847,
      0.007708167191594839,
      0.6330300569534302,
      0.8496727347373962,
      1.6918246746063232,
      3.1561357975006104,
      1.295710802078247,
      1.4850759506225586,
      3.5866074562072754,
      0.18460874259471893,
      1.4952057600021362,
      2.220381736755371,
      1.147429347038269,
      2.851876735687256,
      0.0017608772031962872,
      1.2559187412261963,
      0.1707804650068283,
      2.2521910667419434,
      2.363719940185547,
      1.3318588733673096,
      0.0015556806465610862,
      1.5102722644805908,
      3.4246230125427246,
      2.8120534420013428,
      3.261509895324707,
      1.1269865036010742,
      0.3029445707798004,
      2.469463348388672,
      0.0023156132083386183,
      0.08654271811246872,
      1.805281639099121,
      2.514998435974121,
      1.1729053258895874,
      0.0981421172618866,
      0.6159982681274414,
      2.749772787094116,
      2.889241933822632,
      0.9282094240188599,
      0.015594513155519962,
      1.9568908214569092,
      0.5293959975242615,
      1.0533355474472046,
      0.879676342010498,
      0.2403317093849182,
      1.8572171926498413,
      0.051552895456552505,
      1.537238359451294,
      3.6422436237335205,
      2.4238624572753906,
      0.6399881839752197,
      0.18195612728595734,
      3.3958513736724854,
      2.3872218132019043,
      0.003892864566296339,
      0.9948581457138062,
      2.9904844760894775,
      1.3105206489562988,
      2.677438259124756,
      1.3006235361099243,
      1.947513222694397,
      0.4507793188095093,
      0.12563256919384003,
      0.7224777936935425,
      0.00011598749551922083,
      0.7037075757980347,
      0.3056904077529907,
      1.623640775680542,
      0.06926463544368744,
      0.24647435545921326,
      1.3647377490997314
    ],
    "entropy_g": [
      0.6810579299926758,
      0.32046476006507874,
      1.798421859741211,
      0.8723933696746826,
      0.44018086791038513,
      2.143449306488037,
      0.30477380752563477,
      1.8180475234985352,
      1.6661584377288818,
      2.29396653175354,
      2.917437791824341,
      0.05722770094871521,
      0.012318666093051434,
      2.3739922046661377,
      0.9354637265205383,
      1.7929880619049072,
      0.3935990333557129,
      0.0011593932285904884,
      0.3906403183937073,
      1.2514822483062744,
      1.259331464767456,
      1.6868873834609985,
      1.3759530782699585,
      3.5107932090759277,
      0.001172123709693551,
      2.349919557571411,
      0.1382794976234436,
      1.188732624053955,
      0.18419386446475983,
      0.10184109956026077,
      1.3024258613586426,
      0.5335515737533569,
      1.9745793342590332,
      1.611385464668274,
      0.6977846622467041,
      2.9068403244018555,
      0.6497509479522705,
      0.644256055355072,
      0.3692476153373718,
      0.6757980585098267,
      0.4001430869102478,
      0.043133921921253204,
      1.154213786125183,
      0.0032104719430208206,
      0.023078586906194687,
      0.4109608829021454,
      0.814729630947113,
      1.9044607877731323,
      3.07297945022583,
      1.3006634712219238,
      1.4804106950759888,
      3.039212942123413,
      0.14741943776607513,
      1.8762269020080566,
      2.9498043060302734,
      1.1678626537322998,
      3.1670894622802734,
      0.0023834360763430595,
      1.3111430406570435,
      0.21106572449207306,
      2.3787055015563965,
      2.1640052795410156,
      1.5825920104980469,
      0.023383652791380882,
      1.7149806022644043,
      3.5100362300872803,
      3.0330088138580322,
      2.9221444129943848,
      1.5337005853652954,
      0.32800331711769104,
      2.8359389305114746,
      0.007577081676572561,
      0.1952265202999115,
      1.7448222637176514,
      2.4800894260406494,
      1.1496466398239136,
      0.07127253711223602,
      0.4603453278541565,
      2.775723934173584,
      2.9763050079345703,
      1.1024229526519775,
      0.01748719997704029,
      2.164088487625122,
      0.7161638736724854,
      1.2815120220184326,
      0.8571314811706543,
      0.3612058758735657,
      1.6332015991210938,
      0.12474718689918518,
      1.5110268592834473,
      3.7001798152923584,
      2.6632943153381348,
      0.8156859278678894,
      0.19184263050556183,
      3.457550048828125,
      3.082202434539795,
      0.007222412619739771,
      1.2563347816467285,
      3.5527148246765137,
      1.564542531967163,
      2.606335163116455,
      1.078714370727539,
      2.298799991607666,
      0.5693761110305786,
      0.08826825767755508,
      1.1798607110977173,
      0.012579699978232384,
      1.057703971862793,
      0.49087589979171753,
      1.6098202466964722,
      0.07445016503334045,
      0.3908648192882538,
      1.5368273258209229
    ],
    "entropy_s": [
      0.6580157279968262,
      0.31059324741363525,
      1.7502535581588745,
      0.8374953269958496,
      0.4619809091091156,
      2.224597454071045,
      0.3035958409309387,
      1.7098156213760376,
      1.7076027393341064,
      2.2445874214172363,
      2.8569159507751465,
      0.04535287246108055,
      0.014077084138989449,
      2.318743944168091,
      0.809565544128418,
      1.8364899158477783,
      0.4816001057624817,
      0.000658554257825017,
      0.41271618008613586,
      1.4583648443222046,
      1.2067328691482544,
      1.3499438762664795,
      1.3402918577194214,
      3.431049346923828,
      0.0007093403255566955,
      2.194761037826538,
      0.09429988265037537,
      0.9737191796302795,
      0.16438286006450653,
      0.13510921597480774,
      1.248240351676941,
      0.6593753695487976,
      1.7477190494537354,
      1.5103319883346558,
      0.572640061378479,
      2.7147226333618164,
      0.5555683374404907,
      0.3654053211212158,
      0.3969533443450928,
      0.6035113334655762,
      0.36402302980422974,
      0.055388838052749634,
      1.0753295421600342,
      0.0027677598409354687,
      0.010731687769293785,
      0.5645190477371216,
      0.8483873009681702,
      1.8102712631225586,
      3.0886270999908447,
      1.293604850769043,
      1.48667573928833,
      3.387308120727539,
      0.17129509150981903,
      1.5646400451660156,
      2.415989875793457,
      1.1126682758331299,
      2.871609926223755,
      0.0018845448503270745,
      1.2622013092041016,
      0.16292867064476013,
      2.3063273429870605,
      2.3002490997314453,
      1.3127167224884033,
      0.0009720391826704144,
      1.562516689300537,
      3.4507994651794434,
      2.869030475616455,
      3.202510356903076,
      1.2217392921447754,
      0.3036569058895111,
      2.5563817024230957,
      0.0027399216778576374,
      0.10800962895154953,
      1.8142186403274536,
      2.466261863708496,
      1.171117901802063,
      0.08254652470350266,
      0.5405805110931396,
      2.719128370285034,
      2.8522627353668213,
      0.9637336134910583,
      0.015076639130711555,
      2.0158393383026123,
      0.5856937170028687,
      1.0974736213684082,
      0.8696588277816772,
      0.2564326524734497,
      1.7387651205062866,
      0.0653173178434372,
      1.4768760204315186,
      3.5950112342834473,
      2.4770560264587402,
      0.6818930506706238,
      0.1845259666442871,
      3.520411491394043,
      2.5476181507110596,
      0.004661710001528263,
      1.0393658876419067,
      3.101994037628174,
      1.3514398336410522,
      2.654520273208618,
      1.0926204919815063,
      2.0477614402770996,
      0.44413939118385315,
      0.11068923771381378,
      0.7484991550445557,
      0.00023229543876368552,
      0.7468882203102112,
      0.31529325246810913,
      1.6123852729797363,
      0.0640338733792305,
      0.3278505802154541,
      1.4013066291809082
    ]
  },
  "stats": {
    "counts": {
      "hallu": 3,
      "object": 7,
      "len": 113
    },
    "delta_nll_global": {
      "mean_hallu": 0.2116133173306783,
      "count_hallu": 3,
      "mean_object": -0.008359995404524463,
      "count_object": 7,
      "mean_other": 0.06203612420319843,
      "count_other": 103
    },
    "delta_nll_soft": {
      "mean_hallu": 0.012163440386454264,
      "count_hallu": 3,
      "mean_object": -0.020959266062293733,
      "count_object": 7,
      "mean_other": 0.005580375854593,
      "count_other": 103
    },
    "delta_entropy_global": {
      "mean_hallu": 0.10517966747283936,
      "count_hallu": 3,
      "mean_object": 0.017129287123680115,
      "count_object": 7,
      "mean_other": 0.07965272269946369,
      "count_other": 103
    },
    "delta_entropy_soft": {
      "mean_hallu": -0.028376261393229168,
      "count_hallu": 3,
      "mean_object": -0.010225139558315277,
      "count_object": 7,
      "mean_other": 0.009746308743787558,
      "count_other": 103
    }
  },
  "meta": {
    "lambda_global": 1.0,
    "lam_other": 0.3,
    "lam_object": 0.9,
    "lam_hallu": 0.9,
    "sim_threshold": 0.8
  }
}